nonebot_plugin_bilichat-6.4.2.dist-info/METADATA
nonebot_plugin_bilichat-6.4.2.dist-info/WHEEL
nonebot_plugin_bilichat-6.4.2.dist-info/entry_points.txt
nonebot_plugin_bilichat-6.4.2.dist-info/licenses/LICENSE
nonebot_plugin_bilichat/__init__.py
nonebot_plugin_bilichat/api/__init__.py
nonebot_plugin_bilichat/api/auth.py
nonebot_plugin_bilichat/api/base.py
nonebot_plugin_bilichat/api/config.py
nonebot_plugin_bilichat/base_content_parsing.py
nonebot_plugin_bilichat/command/__init__.py
nonebot_plugin_bilichat/command/base.py
nonebot_plugin_bilichat/command/functions.py
nonebot_plugin_bilichat/command/login.py
nonebot_plugin_bilichat/command/otp.py
nonebot_plugin_bilichat/command/subs.py
nonebot_plugin_bilichat/config.py
nonebot_plugin_bilichat/lib/__init__.py
nonebot_plugin_bilichat/lib/auth.py
nonebot_plugin_bilichat/lib/content_cd.py
nonebot_plugin_bilichat/lib/tools.py
nonebot_plugin_bilichat/migrate.py
nonebot_plugin_bilichat/model/arguments.py
nonebot_plugin_bilichat/model/config.py
nonebot_plugin_bilichat/model/exception.py
nonebot_plugin_bilichat/model/request_api.py
nonebot_plugin_bilichat/model/subscribe.py
nonebot_plugin_bilichat/optional.py
nonebot_plugin_bilichat/request_api/__init__.py
nonebot_plugin_bilichat/request_api/base.py
nonebot_plugin_bilichat/request_api/local.py
nonebot_plugin_bilichat/static/config.yaml
nonebot_plugin_bilichat/static/html/404.html
nonebot_plugin_bilichat/static/html/404/index.html
nonebot_plugin_bilichat/static/html/_next/static/chunks/341.2903e54d3da731c1.js
nonebot_plugin_bilichat/static/html/_next/static/chunks/472.a3826d29d6854395.js
nonebot_plugin_bilichat/static/html/_next/static/chunks/4bd1b696-7169861da40f817b.js
nonebot_plugin_bilichat/static/html/_next/static/chunks/684-5a9ecabb2c5a99ca.js
nonebot_plugin_bilichat/static/html/_next/static/chunks/824-6ec2445d552b1a95.js
nonebot_plugin_bilichat/static/html/_next/static/chunks/app/_not-found/page-7b137d85f9de4771.js
nonebot_plugin_bilichat/static/html/_next/static/chunks/app/layout-79de70319398d209.js
nonebot_plugin_bilichat/static/html/_next/static/chunks/app/page-9b37dd38ece481eb.js
nonebot_plugin_bilichat/static/html/_next/static/chunks/framework-29ac49a6a3fd316f.js
nonebot_plugin_bilichat-6.4.2.dist-info/RECORD
