Metadata-Version: 2.1
Name: nonebot-plugin-bilichat
Version: 6.4.2
Summary: 全功能的 bilibili 内容解析器及订阅器
Author-Email: djkcyl <cyl@cyllive.cn>, Well404 <well_404@outlook.com>
License: AGPL3.0
Requires-Python: <4.0,>=3.10
Requires-Dist: nonebot-plugin-localstore>=0.7.4
Requires-Dist: nonebot2[fastapi,websockets]
Requires-Dist: httpx>=0.28.1
Requires-Dist: nonebot-plugin-apscheduler>=0.5.0
Requires-Dist: python-multipart>=0.0.20
Requires-Dist: nonebot-plugin-alconna>=0.59.0
Requires-Dist: nonebot-plugin-sentry>=2.0.0
Requires-Dist: packaging>=25.0
Requires-Dist: pydantic>=2.11.3
Requires-Dist: nonebot-plugin-uninfo>=0.7.3
Requires-Dist: pyyaml>=6.0.2
Requires-Dist: pypng>=0.20220715.0
Requires-Dist: qrcode>=8.1
Requires-Dist: pytz>=2025.2
Requires-Dist: deepdiff>=8.4.2
Requires-Dist: python-jose[cryptography]>=3.3.0
Requires-Dist: pyotp>=2.9.0
Provides-Extra: api
Requires-Dist: bilichat-request>=0.4.0; extra == "api"
